nut2.py
nut2-2.1.0.dist-info/METADATA
nut2-2.1.0.dist-info/RECORD
nut2-2.1.0.dist-info/WHEEL
nut2-2.1.0.dist-info/top_level.txt
