Metadata-Version: 2.1
Name: nut2
Version: 2.1.0
Summary: A Python abstraction class to access NUT servers.
Home-page: https://github.com/rshipp/python-nut2
Author: Ryan Shipp
Author-email: python@rshipp.com
License: GPL3
Platform: UNKNOWN
Classifier: Intended Audience :: Developers
Classifier: Intended Audience :: Information Technology
Classifier: Intended Audience :: System Administrators
Classifier: License :: OSI Approved :: GNU General Public License v3 or later (GPLv3+)
Classifier: Operating System :: OS Independent
Classifier: Programming Language :: Python
Classifier: Programming Language :: Python :: 2.7
Classifier: Programming Language :: Python :: 3
Classifier: Topic :: Software Development :: Libraries
Classifier: Topic :: System :: Power (UPS)
Classifier: Topic :: System :: Systems Administration
